pingdat/__init__.py
pingdat/__main__.py
pingdat/config.py
pingdat/version.py
pingdat-1.6.3.dist-info/METADATA
pingdat-1.6.3.dist-info/WHEEL
pingdat-1.6.3.dist-info/entry_points.txt
pingdat-1.6.3.dist-info/licenses/LICENSE
pingdat-1.6.3.dist-info/RECORD
