Metadata-Version: 2.4
Name: pingdat
Version: 1.6.3
Summary: A simple ping exporter for Prometheus metrics.
Author-email: jheddings <jheddings@gmail.com>
License-Expression: MIT
License-File: LICENSE
Requires-Python: <4,>=3.10
Requires-Dist: click<9,>=8.2.1
Requires-Dist: ping3<6,>=5.1.5
Requires-Dist: prometheus-client<0.23,>=0.22.1
Requires-Dist: pydantic<3,>=2.11.7
Requires-Dist: pyyaml<7,>=6.0.2
Requires-Dist: requests<3,>=2.32.5
